parse_it/__init__.py
parse_it/parser.py
parse_it/command_line_args/__init__.py
parse_it/command_line_args/command_line_args.py
parse_it/envvars/__init__.py
parse_it/envvars/envvars.py
parse_it/file/__init__.py
parse_it/file/env.py
parse_it/file/file_reader.py
parse_it/file/hcl.py
parse_it/file/ini.py
parse_it/file/json.py
parse_it/file/toml.py
parse_it/file/xml.py
parse_it/file/yaml.py
parse_it/type_estimate/__init__.py
parse_it/type_estimate/type_estimate.py
parse_it-2025.9.14.13.29.data/scripts/setup.py
parse_it-2025.9.14.13.29.dist-info/licenses/LICENSE
test/__init__.py
test/test_prase_it.py
parse_it-2025.9.14.13.29.dist-info/METADATA
parse_it-2025.9.14.13.29.dist-info/WHEEL
parse_it-2025.9.14.13.29.dist-info/top_level.txt
parse_it-2025.9.14.13.29.dist-info/RECORD
