Metadata-Version: 2.4
Name: parse_it
Version: 2025.9.14.13.29
Summary: A python library for parsing multiple types of config files, envvars and command line arguments which takes the headache out of setting app configurations.
Home-page: https://github.com/naorlivne/parse_it
Author: Naor Livne
Author-email: naorlivne@gmail.com
License: LGPLv3
Keywords: parse_it parsing parse parser yaml json xml toml ini cfg hcl envvar environment_variable config cli_args command_line_arguments tml yml configuration configuration_file
Classifier: Development Status :: 5 - Production/Stable
Classifier: Environment :: Other Environment
Classifier: License :: OSI Approved :: GNU Lesser General Public License v3 (LGPLv3)
Classifier: Operating System :: OS Independent
Classifier: Intended Audience :: Developers
Classifier: Intended Audience :: System Administrators
Classifier: Topic :: Software Development :: Libraries :: Python Modules
Classifier: Programming Language :: Python
Classifier: Programming Language :: Python :: 3
Classifier: Programming Language :: Python :: 3.6
Classifier: Programming Language :: Python :: 3.7
Classifier: Programming Language :: Python :: 3.8
Classifier: Programming Language :: Python :: 3.9
Classifier: Programming Language :: Python :: 3.10
Classifier: Programming Language :: Python :: 3.11
Classifier: Programming Language :: Python :: 3.12
Classifier: Programming Language :: Python :: 3.13
License-File: LICENSE
Requires-Dist: PyYAML
Requires-Dist: toml
Requires-Dist: configobj
Requires-Dist: xmltodict
Requires-Dist: pyhcl
Requires-Dist: python-dotenv
Requires-Dist: dpath
Provides-Extra: typing
Requires-Dist: typing; extra == "typing"
Dynamic: author
Dynamic: author-email
Dynamic: classifier
Dynamic: description
Dynamic: description-content-type
Dynamic: home-page
Dynamic: keywords
Dynamic: license
Dynamic: license-file
Dynamic: provides-extra
Dynamic: requires-dist
Dynamic: summary
